async_bithumb/__init__.py
async_bithumb/client.py
async_bithumb/core.py
async_bithumb/errors.py
async_bithumb/util.py
async_bithumb/websocket.py
async_bithumb-1.0.6.dist-info/LICENSE
async_bithumb-1.0.6.dist-info/METADATA
async_bithumb-1.0.6.dist-info/WHEEL
async_bithumb-1.0.6.dist-info/top_level.txt
async_bithumb-1.0.6.dist-info/RECORD
